dwdweather.py
setup.py
dwdweather.egg-info/PKG-INFO
dwdweather.egg-info/SOURCES.txt
dwdweather.egg-info/dependency_links.txt
dwdweather.egg-info/entry_points.txt
dwdweather.egg-info/top_level.txt