Metadata-Version: 1.0
Name: dwdweather
Version: 0.4
Summary: Inofficial DWD weather data client (Deutscher Wetterdienst)
Home-page: http://github.com/marians/dwd-weather
Author: Marian Steinbach
Author-email: marian@sendung.de
License: UNKNOWN
Platform: UNKNOWN
